setup.py
electrical_calendar/__init__.py
electrical_calendar/electrical.py
electrical_calendar/omie.py
electrical_calendar.egg-info/PKG-INFO
electrical_calendar.egg-info/SOURCES.txt
electrical_calendar.egg-info/dependency_links.txt
electrical_calendar.egg-info/requires.txt
electrical_calendar.egg-info/top_level.txt