Metadata-Version: 1.1
Name: electrical-calendar
Version: 0.4
Summary: Electrical sector holidays and workdays using workalendar. Spain and Portugal data
Home-page: https://www.gisce.net
Author: GISCE Enginyeria, SL
Author-email: devel@gisce.net
License: General Public Licence 3
Platform: UNKNOWN
Provides: electrical_calendar
